sideshift_py/__init__.py
sideshift_py-0.1.0.dist-info/METADATA
sideshift_py-0.1.0.dist-info/WHEEL
sideshift_py-0.1.0.dist-info/RECORD
